pylelemmatize/__init__.py
pylelemmatize/abstract_mapper.py
pylelemmatize/all_charsets.py
pylelemmatize/char_distance.py
pylelemmatize/charset_ascii.py
pylelemmatize/charset_greek.py
pylelemmatize/charset_iso.py
pylelemmatize/charset_mes.py
pylelemmatize/charset_mufi.py
pylelemmatize/demapper_lstm.py
pylelemmatize/demapper_lstm_ctc.py
pylelemmatize/fast_mapper.py
pylelemmatize/htr_postcorrection.py
pylelemmatize/main_functions.py
pylelemmatize/many_to_more.py
pylelemmatize/mapper_ds.py
pylelemmatize/philogeny.py
pylelemmatize/pylelemmatize_torch.py
pylelemmatize/substitution_augmenter.py
pylelemmatize/util.py
pylelemmatize/version.py
pylelemmatize/xml_util.py
pylelemmatize-0.1.1.dist-info/licenses/LICENSE
pylelemmatize_torch/__init__.py
pylelemmatize-0.1.1.dist-info/METADATA
pylelemmatize-0.1.1.dist-info/WHEEL
pylelemmatize-0.1.1.dist-info/entry_points.txt
pylelemmatize-0.1.1.dist-info/top_level.txt
pylelemmatize-0.1.1.dist-info/RECORD
