Metadata-Version: 2.4
Name: pylelemmatize
Version: 0.1.1
Summary: A set utilities for hadling alphabets of corpora and OCR/HTR datasets
Home-page: https://github.com/anguelos/pylelemmatize
Author: Anguelos Nicolaou
Author-email: anguelos.nicolaou@gmail.com
Classifier: Programming Language :: Python :: 3
Classifier: License :: OSI Approved :: MIT License
Classifier: Operating System :: OS Independent
Requires-Python: >=3.9
License-File: LICENSE
Requires-Dist: numpy
Requires-Dist: unidecode
Requires-Dist: fargv
Requires-Dist: matplotlib
Requires-Dist: seaborn
Requires-Dist: scipy
Requires-Dist: tqdm
Requires-Dist: networkx
Requires-Dist: lxml
Dynamic: author
Dynamic: author-email
Dynamic: classifier
Dynamic: description
Dynamic: description-content-type
Dynamic: home-page
Dynamic: license-file
Dynamic: requires-dist
Dynamic: requires-python
Dynamic: summary
